odoo/addons/agreement_account/README.rst
odoo/addons/agreement_account/__init__.py
odoo/addons/agreement_account/__manifest__.py
odoo/addons/agreement_account/i18n/agreement_account.pot
odoo/addons/agreement_account/i18n/es.po
odoo/addons/agreement_account/i18n/es_AR.po
odoo/addons/agreement_account/i18n/it.po
odoo/addons/agreement_account/models/__init__.py
odoo/addons/agreement_account/models/account_move.py
odoo/addons/agreement_account/models/agreement.py
odoo/addons/agreement_account/readme/CONTRIBUTORS.rst
odoo/addons/agreement_account/readme/DESCRIPTION.rst
odoo/addons/agreement_account/security/ir.model.access.csv
odoo/addons/agreement_account/static/description/icon.png
odoo/addons/agreement_account/static/description/index.html
odoo/addons/agreement_account/tests/__init__.py
odoo/addons/agreement_account/tests/test_agreement.py
odoo/addons/agreement_account/views/account_move.xml
odoo/addons/agreement_account/views/agreement.xml
odoo14_addon_agreement_account-14.0.1.0.1.dev13.dist-info/METADATA
odoo14_addon_agreement_account-14.0.1.0.1.dev13.dist-info/WHEEL
odoo14_addon_agreement_account-14.0.1.0.1.dev13.dist-info/top_level.txt
odoo14_addon_agreement_account-14.0.1.0.1.dev13.dist-info/RECORD
